README.md
copilotcloud_rl/__init__.py
copilotcloud_rl/client.py
copilotcloud_rl-0.1.1.dist-info/METADATA
copilotcloud_rl-0.1.1.dist-info/WHEEL
copilotcloud_rl-0.1.1.dist-info/licenses/LICENSE
copilotcloud_rl-0.1.1.dist-info/RECORD
