Metadata-Version: 2.4
Name: copilotcloud-rl
Version: 0.1.1
Summary: Python client for CopilotCloud Reinforcement Learning context API
Project-URL: Homepage, https://github.com/CopilotKit/copilotcloud-rl
Project-URL: Repository, https://github.com/CopilotKit/copilotcloud-rl
Author-email: Luis Valdes <luis@copilotkit.ai>
License: MIT
License-File: LICENSE
Keywords: ai,copilotcloud,copilotkit,reinforcement-learning,rl
Classifier: Intended Audience :: Developers
Classifier: License :: OSI Approved :: MIT License
Classifier: Programming Language :: Python :: 3
Classifier: Programming Language :: Python :: 3 :: Only
Classifier: Programming Language :: Python :: 3.8
Classifier: Programming Language :: Python :: 3.9
Classifier: Programming Language :: Python :: 3.10
Classifier: Programming Language :: Python :: 3.11
Classifier: Programming Language :: Python :: 3.12
Classifier: Topic :: Software Development :: Libraries :: Python Modules
Requires-Python: >=3.8
Requires-Dist: requests<3,>=2.31.0
Requires-Dist: typing-extensions>=4.8.0; python_version < '3.11'
